rudipy/__init__.py
rudipy/debug.py
rudipy/devices/M5.py
rudipy/devices/__init__.py
rudipy/enumeration.py
rudipy/peripherals/M5Units.py
rudipy/peripherals/__init__.py
rudipy-0.1.1.dist-info/METADATA
rudipy-0.1.1.dist-info/WHEEL
rudipy-0.1.1.dist-info/RECORD
